robotathome/__init__.py
robotathome/_version.py
robotathome/helpers.py
robotathome/log.py
robotathome/core/__init__.py
robotathome/core/df.py
robotathome/core/reader.py
robotathome/cv/__init__.py
robotathome/cv/_greetings.py
robotathome/cv/gluoncv.py
robotathome/cv/opencv.py
robotathome-1.1.9.data/data/robotathome/notebooks/05-Google-colab-drive.ipynb
robotathome-1.1.9.data/data/robotathome/notebooks/10-Download-and-install.ipynb
robotathome-1.1.9.data/data/robotathome/notebooks/100-Iterating-over-RGBD-images.ipynb
robotathome-1.1.9.data/data/robotathome/notebooks/110-Concatenating-images-from-multiple-cameras.ipynb
robotathome-1.1.9.data/data/robotathome/notebooks/120-Making-a-video.ipynb
robotathome-1.1.9.data/data/robotathome/notebooks/130-Processing-images-with-YOLO.ipynb
robotathome-1.1.9.data/data/robotathome/notebooks/140-Loading-dataset-in-Google-Colab.ipynb
robotathome-1.1.9.data/data/robotathome/notebooks/150-Segmentation-with-Detectron2.ipynb
robotathome-1.1.9.data/data/robotathome/notebooks/20-Before-starting-the-logging-system.ipynb
robotathome-1.1.9.data/data/robotathome/notebooks/30-Getting-started-Framework-data.ipynb
robotathome-1.1.9.data/data/robotathome/notebooks/40-Captured-data.ipynb
robotathome-1.1.9.data/data/robotathome/notebooks/50-RGBD-observations.ipynb
robotathome-1.1.9.data/data/robotathome/notebooks/60-Lsrscan-observations.ipynb
robotathome-1.1.9.data/data/robotathome/notebooks/70-Scenes.ipynb
robotathome-1.1.9.data/data/robotathome/notebooks/80-Characterized-observations.ipynb
robotathome-1.1.9.data/data/robotathome/notebooks/90-The-config-file.ipynb
robotathome-1.1.9.data/data/robotathome/schema/rh_schema_brief.pdf
robotathome-1.1.9.data/data/robotathome/schema/rh_schema_full.pdf
src/__init__.py
src/_version.py
src/helpers.py
src/log.py
src/core/__init__.py
src/core/df.py
src/core/reader.py
src/cv/__init__.py
src/cv/_greetings.py
src/cv/gluoncv.py
src/cv/opencv.py
robotathome-1.1.9.dist-info/LICENSE
robotathome-1.1.9.dist-info/METADATA
robotathome-1.1.9.dist-info/WHEEL
robotathome-1.1.9.dist-info/top_level.txt
robotathome-1.1.9.dist-info/RECORD
