Metadata-Version: 2.1
Name: robotathome
Version: 1.1.9
Summary: This package provides a Python Toolbox with a set of functions to assist in the management of Robot@Home2 Dataset
Home-page: https://github.com/goyoambrosio/RobotAtHome2
Author: G. Ambrosio-Cestero
Author-email: gambrosio@uma.es
License: MIT
Keywords: toolbox dataset database relational model mobile robotics computer vision
Platform: Windows
Platform: Linux
Classifier: Programming Language :: Python :: 3
Classifier: License :: OSI Approved :: MIT License
Classifier: Operating System :: OS Independent
Requires-Python: >=3.7
License-File: LICENSE
Requires-Dist: humanize
Requires-Dist: click
Requires-Dist: urllib3
Requires-Dist: requests
Requires-Dist: tqdm
Requires-Dist: loguru
Requires-Dist: pandas
Requires-Dist: numpy
Provides-Extra: cv
Requires-Dist: opencv-python ; extra == 'cv'
Requires-Dist: opencv-contrib-python ; extra == 'cv'
Provides-Extra: full
Requires-Dist: matplotlib (>=3) ; extra == 'full'
Requires-Dist: notebook ; extra == 'full'
Requires-Dist: ipywidgets ; extra == 'full'
Requires-Dist: opencv-python ; extra == 'full'
Requires-Dist: opencv-contrib-python ; extra == 'full'
Provides-Extra: interactive
Requires-Dist: matplotlib (>=3) ; extra == 'interactive'
Requires-Dist: notebook ; extra == 'interactive'
Requires-Dist: ipywidgets ; extra == 'interactive'
